rst2ansi/__init__.py
rst2ansi/ansi.py
rst2ansi/functional.py
rst2ansi/get_terminal_size.py
rst2ansi/table.py
rst2ansi/unicode.py
rst2ansi/visitor.py
rst2ansi/wrap.py
rst2ansi-0.1.5.data/scripts/rst2ansi
rst2ansi-0.1.5.dist-info/DESCRIPTION.rst
rst2ansi-0.1.5.dist-info/METADATA
rst2ansi-0.1.5.dist-info/RECORD
rst2ansi-0.1.5.dist-info/WHEEL
rst2ansi-0.1.5.dist-info/metadata.json
rst2ansi-0.1.5.dist-info/top_level.txt
