Metadata-Version: 1.1
Name: rst2ansi
Version: 0.1.5
Summary: A rst converter to ansi-decorated console output
Home-page: https://github.com/Snaipe/python-rst-to-ansi
Author: Snaipe
Author-email: franklinmathieu@gmail.com
License: MIT
Keywords: rst restructuredtext ansi console code converter
Platform: UNKNOWN
Classifier: Development Status :: 4 - Beta
Classifier: Environment :: Console
Classifier: Intended Audience :: Developers
Classifier: Intended Audience :: End Users/Desktop
Classifier: License :: OSI Approved :: MIT License
Classifier: Operating System :: OS Independent
Classifier: Programming Language :: Python :: 2.7
Classifier: Programming Language :: Python :: 3
Classifier: Programming Language :: Python :: 3.3
Classifier: Programming Language :: Python :: 3.4
Classifier: Programming Language :: Python :: 3.5
Classifier: Topic :: Software Development :: Libraries :: Python Modules
Classifier: Topic :: Text Processing :: Markup
Classifier: Topic :: Utilities
Requires: docutils
